robout/__init__.py
robout/robout_scaler.py
robout-0.1.1.dist-info/LICENSE
robout-0.1.1.dist-info/METADATA
robout-0.1.1.dist-info/WHEEL
robout-0.1.1.dist-info/top_level.txt
robout-0.1.1.dist-info/RECORD
